odoo/addons/rental_pricelist_interval/README.rst
odoo/addons/rental_pricelist_interval/__init__.py
odoo/addons/rental_pricelist_interval/__manifest__.py
odoo/addons/rental_pricelist_interval/hooks.py
odoo/addons/rental_pricelist_interval/README/CONFIGURATION.rst
odoo/addons/rental_pricelist_interval/README/CONTRIBUTORS.rst
odoo/addons/rental_pricelist_interval/README/DESCRIPTION.rst
odoo/addons/rental_pricelist_interval/README/HISTORY.rst
odoo/addons/rental_pricelist_interval/README/USAGE.rst
odoo/addons/rental_pricelist_interval/data/product_pricelist_data.xml
odoo/addons/rental_pricelist_interval/data/product_uom_data.xml
odoo/addons/rental_pricelist_interval/i18n/de.po
odoo/addons/rental_pricelist_interval/i18n/it.po
odoo/addons/rental_pricelist_interval/i18n/rental_pricelist_interval.pot
odoo/addons/rental_pricelist_interval/models/__init__.py
odoo/addons/rental_pricelist_interval/models/product.py
odoo/addons/rental_pricelist_interval/models/res_company.py
odoo/addons/rental_pricelist_interval/models/sale.py
odoo/addons/rental_pricelist_interval/security/ir.model.access.csv
odoo/addons/rental_pricelist_interval/static/description/icon.png
odoo/addons/rental_pricelist_interval/static/description/index.html
odoo/addons/rental_pricelist_interval/tests/__init__.py
odoo/addons/rental_pricelist_interval/tests/test_rental_pricelist.py
odoo/addons/rental_pricelist_interval/views/product_pricelist_view.xml
odoo/addons/rental_pricelist_interval/views/product_view.xml
odoo/addons/rental_pricelist_interval/views/res_company_view.xml
odoo14_addon_rental_pricelist_interval-14.0.1.0.1.dev10.dist-info/METADATA
odoo14_addon_rental_pricelist_interval-14.0.1.0.1.dev10.dist-info/WHEEL
odoo14_addon_rental_pricelist_interval-14.0.1.0.1.dev10.dist-info/top_level.txt
odoo14_addon_rental_pricelist_interval-14.0.1.0.1.dev10.dist-info/RECORD
